csvpandas/__init__.py
csvpandas/utils.py
csvpandas/version.py
csvpandas/subcommands/__init__.py
csvpandas/subcommands/cut.py
csvpandas/subcommands/deduplicate.py
csvpandas/subcommands/grep.py
csvpandas/subcommands/join.py
csvpandas/subcommands/look.py
csvpandas/subcommands/report.py
csvpandas/subcommands/sample.py
csvpandas/subcommands/sort.py
csvpandas/subcommands/stack.py
csvpandas/subcommands/tocsv.py
csvpandas-0.0.5.dist-info/DESCRIPTION.rst
csvpandas-0.0.5.dist-info/METADATA
csvpandas-0.0.5.dist-info/RECORD
csvpandas-0.0.5.dist-info/WHEEL
csvpandas-0.0.5.dist-info/entry_points.txt
csvpandas-0.0.5.dist-info/metadata.json
csvpandas-0.0.5.dist-info/pbr.json
csvpandas-0.0.5.dist-info/top_level.txt
