Metadata-Version: 2.0
Name: csvpandas
Version: 0.0.5
Summary: Interface to manipulate csv files as Pandas DataFrames.
Home-page: https://github.com/crosenth/csvpandas
Author: Chris Rosenthal
Author-email: crosenth@gmail.com
License: GPLv3
Platform: UNKNOWN
Classifier: License :: OSI Approved :: GNU General Public License v3 (GPLv3)
Classifier: Development Status :: 1 - Planning
Requires-Dist: pandas (>=0.17)
